{
  "version": "1.0",
  "noteSpeed": 10.0,
  "notes": [
    { "type": "normal", "beat": 2.0, "duration": 0, "lane": 1, "row": 1, "direction": "down", "color": "red" },
    { "type": "normal", "beat": 4.0, "duration": 0, "lane": 2, "row": 1, "direction": "down", "color": "blue" },
    { "type": "normal", "beat": 6.0, "duration": 0, "lane": 1, "row": 0, "direction": "right", "color": "red" },
    { "type": "normal", "beat": 8.0, "duration": 0, "lane": 2, "row": 0, "direction": "left", "color": "blue" },
    { "type": "long", "beat": 10.0, "duration": 4.0, "lane": 1, "row": 1, "direction": "any", "color": "red" },
    { "type": "long", "beat": 10.0, "duration": 4.0, "lane": 2, "row": 1, "direction": "any", "color": "blue" },
    { "type": "normal", "beat": 16.0, "duration": 0, "lane": 0, "row": 1, "direction": "right", "color": "red" },
    { "type": "normal", "beat": 17.0, "duration": 0, "lane": 1, "row": 1, "direction": "right", "color": "red" },
    { "type": "normal", "beat": 18.0, "duration": 0, "lane": 3, "row": 1, "direction": "left", "color": "blue" },
    { "type": "normal", "beat": 19.0, "duration": 0, "lane": 2, "row": 1, "direction": "left", "color": "blue" },
    { "type": "normal", "beat": 20.0, "duration": 0, "lane": 1, "row": 0, "direction": "up", "color": "red" },
    { "type": "normal", "beat": 20.0, "duration": 0, "lane": 2, "row": 0, "direction": "up", "color": "blue" },
    { "type": "normal", "beat": 22.0, "duration": 0, "lane": 0, "row": 2, "direction": "downRight", "color": "red" },
    { "type": "normal", "beat": 24.0, "duration": 0, "lane": 3, "row": 2, "direction": "downLeft", "color": "blue" },
    { "type": "normal", "beat": 26.0, "duration": 0, "lane": 1, "row": 1, "direction": "any", "color": "red" },
    { "type": "normal", "beat": 28.0, "duration": 0, "lane": 2, "row": 1, "direction": "any", "color": "blue" },
    { "type": "normal", "beat": 30.0, "duration": 0, "lane": 0, "row": 0, "direction": "upRight", "color": "red" },
    { "type": "normal", "beat": 32.0, "duration": 0, "lane": 3, "row": 0, "direction": "upLeft", "color": "blue" },
    { "type": "long", "beat": 34.0, "duration": 6.0, "lane": 0, "row": 1, "direction": "any", "color": "red" },
    { "type": "long", "beat": 34.0, "duration": 6.0, "lane": 3, "row": 1, "direction": "any", "color": "blue" },
    { "type": "normal", "beat": 42.0, "duration": 0, "lane": 1, "row": 1, "direction": "down", "color": "red" },
    { "type": "normal", "beat": 43.0, "duration": 0, "lane": 2, "row": 1, "direction": "down", "color": "blue" },
    { "type": "normal", "beat": 44.0, "duration": 0, "lane": 1, "row": 1, "direction": "up", "color": "red" },
    { "type": "normal", "beat": 45.0, "duration": 0, "lane": 2, "row": 1, "direction": "up", "color": "blue" },
    { "type": "normal", "beat": 46.0, "duration": 0, "lane": 1, "row": 1, "direction": "left", "color": "red" },
    { "type": "normal", "beat": 47.0, "duration": 0, "lane": 2, "row": 1, "direction": "right", "color": "blue" },
    { "type": "normal", "beat": 48.0, "duration": 0, "lane": 1, "row": 1, "direction": "any", "color": "red" },
    { "type": "normal", "beat": 49.0, "duration": 0, "lane": 2, "row": 1, "direction": "any", "color": "blue" },
    { "type": "normal", "beat": 52.0, "duration": 0, "lane": 0, "row": 0, "direction": "up", "color": "red" },
    { "type": "normal", "beat": 53.0, "duration": 0, "lane": 3, "row": 0, "direction": "up", "color": "blue" },
    { "type": "normal", "beat": 54.0, "duration": 0, "lane": 0, "row": 2, "direction": "down", "color": "red" },
    { "type": "normal", "beat": 55.0, "duration": 0, "lane": 3, "row": 2, "direction": "down", "color": "blue" },
    { "type": "long", "beat": 58.0, "duration": 10.0, "lane": 1, "row": 1, "direction": "any", "color": "red" },
    { "type": "long", "beat": 58.0, "duration": 10.0, "lane": 2, "row": 1, "direction": "any", "color": "blue" },
    { "type": "normal", "beat": 70.0, "duration": 0, "lane": 1, "row": 0, "direction": "any", "color": "red" },
    { "type": "normal", "beat": 71.0, "duration": 0, "lane": 2, "row": 0, "direction": "any", "color": "blue" },
    { "type": "normal", "beat": 72.0, "duration": 0, "lane": 1, "row": 2, "direction": "any", "color": "red" },
    { "type": "normal", "beat": 73.0, "duration": 0, "lane": 2, "row": 2, "direction": "any", "color": "blue" },
    { "type": "normal", "beat": 74.0, "duration": 0, "lane": 0, "row": 1, "direction": "any", "color": "red" },
    { "type": "normal", "beat": 75.0, "duration": 0, "lane": 3, "row": 1, "direction": "any", "color": "blue" },
    { "type": "normal", "beat": 78.0, "duration": 0, "lane": 1, "row": 1, "direction": "down", "color": "red" },
    { "type": "normal", "beat": 78.5, "duration": 0, "lane": 2, "row": 1, "direction": "down", "color": "blue" },
    { "type": "normal", "beat": 79.0, "duration": 0, "lane": 1, "row": 1, "direction": "up", "color": "red" },
    { "type": "normal", "beat": 79.5, "duration": 0, "lane": 2, "row": 1, "direction": "up", "color": "blue" },
    { "type": "normal", "beat": 80.0, "duration": 0, "lane": 1, "row": 1, "direction": "down", "color": "red" },
    { "type": "normal", "beat": 80.5, "duration": 0, "lane": 2, "row": 1, "direction": "down", "color": "blue" },
    { "type": "normal", "beat": 81.0, "duration": 0, "lane": 1, "row": 1, "direction": "up", "color": "red" },
    { "type": "normal", "beat": 81.5, "duration": 0, "lane": 2, "row": 1, "direction": "up", "color": "blue" },
    { "type": "long", "beat": 84.0, "duration": 8.0, "lane": 0, "row": 0, "direction": "any", "color": "red" },
    { "type": "long", "beat": 84.0, "duration": 8.0, "lane": 3, "row": 0, "direction": "any", "color": "blue" },
    { "type": "normal", "beat": 94.0, "duration": 0, "lane": 1, "row": 1, "direction": "left", "color": "red" },
    { "type": "normal", "beat": 95.0, "duration": 0, "lane": 2, "row": 1, "direction": "right", "color": "blue" },
    { "type": "normal", "beat": 96.0, "duration": 0, "lane": 1, "row": 1, "direction": "right", "color": "red" },
    { "type": "normal", "beat": 97.0, "duration": 0, "lane": 2, "row": 1, "direction": "left", "color": "blue" },
    { "type": "normal", "beat": 100.0, "duration": 0, "lane": 1, "row": 2, "direction": "down", "color": "red" },
    { "type": "normal", "beat": 100.0, "duration": 0, "lane": 2, "row": 2, "direction": "down", "color": "blue" },
    { "type": "normal", "beat": 102.0, "duration": 0, "lane": 1, "row": 0, "direction": "up", "color": "red" },
    { "type": "normal", "beat": 102.0, "duration": 0, "lane": 2, "row": 0, "direction": "up", "color": "blue" },
    { "type": "long", "beat": 106.0, "duration": 12.0, "lane": 1, "row": 1, "direction": "any", "color": "red" },
    { "type": "long", "beat": 106.0, "duration": 12.0, "lane": 2, "row": 1, "direction": "any", "color": "blue" },
    { "type": "normal", "beat": 120.0, "duration": 0, "lane": 0, "row": 0, "direction": "any", "color": "red" },
    { "type": "normal", "beat": 121.0, "duration": 0, "lane": 1, "row": 0, "direction": "any", "color": "red" },
    { "type": "normal", "beat": 122.0, "duration": 0, "lane": 2, "row": 0, "direction": "any", "color": "blue" },
    { "type": "normal", "beat": 123.0, "duration": 0, "lane": 3, "row": 0, "direction": "any", "color": "blue" },
    { "type": "normal", "beat": 126.0, "duration": 0, "lane": 1, "row": 1, "direction": "down", "color": "red" },
    { "type": "normal", "beat": 127.0, "duration": 0, "lane": 2, "row": 1, "direction": "down", "color": "blue" },
    { "type": "normal", "beat": 128.0, "duration": 0, "lane": 0, "row": 1, "direction": "left", "color": "red" },
    { "type": "normal", "beat": 129.0, "duration": 0, "lane": 3, "row": 1, "direction": "right", "color": "blue" },
    { "type": "long", "beat": 132.0, "duration": 20.0, "lane": 1, "row": 1, "direction": "any", "color": "red" },
    { "type": "long", "beat": 132.0, "duration": 20.0, "lane": 2, "row": 1, "direction": "any", "color": "blue" },
    { "type": "normal", "beat": 155.0, "duration": 0, "lane": 1, "row": 0, "direction": "up", "color": "red" },
    { "type": "normal", "beat": 156.0, "duration": 0, "lane": 2, "row": 0, "direction": "up", "color": "blue" },
    { "type": "normal", "beat": 157.0, "duration": 0, "lane": 1, "row": 2, "direction": "down", "color": "red" },
    { "type": "normal", "beat": 158.0, "duration": 0, "lane": 2, "row": 2, "direction": "down", "color": "blue" },
    { "type": "normal", "beat": 160.0, "duration": 0, "lane": 0, "row": 1, "direction": "left", "color": "red" },
    { "type": "normal", "beat": 161.0, "duration": 0, "lane": 3, "row": 1, "direction": "right", "color": "blue" },
    { "type": "normal", "beat": 162.0, "duration": 0, "lane": 1, "row": 1, "direction": "right", "color": "red" },
    { "type": "normal", "beat": 163.0, "duration": 0, "lane": 2, "row": 1, "direction": "left", "color": "blue" },
    { "type": "long", "beat": 166.0, "duration": 15.0, "lane": 0, "row": 2, "direction": "any", "color": "red" },
    { "type": "long", "beat": 166.0, "duration": 15.0, "lane": 3, "row": 2, "direction": "any", "color": "blue" },
    { "type": "normal", "beat": 185.0, "duration": 0, "lane": 1, "row": 1, "direction": "any", "color": "red" },
    { "type": "normal", "beat": 186.0, "duration": 0, "lane": 2, "row": 1, "direction": "any", "color": "blue" },
    { "type": "normal", "beat": 187.0, "duration": 0, "lane": 1, "row": 1, "direction": "any", "color": "red" },
    { "type": "normal", "beat": 188.0, "duration": 0, "lane": 2, "row": 1, "direction": "any", "color": "blue" },
    { "type": "normal", "beat": 192.0, "duration": 0, "lane": 0, "row": 0, "direction": "upRight", "color": "red" },
    { "type": "normal", "beat": 193.0, "duration": 0, "lane": 3, "row": 0, "direction": "upLeft", "color": "blue" },
    { "type": "normal", "beat": 194.0, "duration": 0, "lane": 0, "row": 2, "direction": "downRight", "color": "red" },
    { "type": "normal", "beat": 195.0, "duration": 0, "lane": 3, "row": 2, "direction": "downLeft", "color": "blue" },
    { "type": "long", "beat": 200.0, "duration": 30.0, "lane": 1, "row": 1, "direction": "any", "color": "red" },
    { "type": "long", "beat": 200.0, "duration": 30.0, "lane": 2, "row": 1, "direction": "any", "color": "blue" },
    { "type": "normal", "beat": 235.0, "duration": 0, "lane": 1, "row": 1, "direction": "any", "color": "red" },
    { "type": "normal", "beat": 236.0, "duration": 0, "lane": 2, "row": 1, "direction": "any", "color": "blue" },
    { "type": "normal", "beat": 237.0, "duration": 0, "lane": 1, "row": 1, "direction": "any", "color": "red" },
    { "type": "normal", "beat": 238.0, "duration": 0, "lane": 2, "row": 1, "direction": "any", "color": "blue" },
    { "type": "normal", "beat": 240.0, "duration": 0, "lane": 1, "row": 1, "direction": "any", "color": "red" },
    { "type": "normal", "beat": 240.0, "duration": 0, "lane": 2, "row": 1, "direction": "any", "color": "blue" }
  ]
}
